deephaven_plugin_voice_table/__init__.py
deephaven_plugin_voice_table/command_decoder.py
deephaven_plugin_voice_table/voice_table.py
deephaven_plugin_voice_table-0.0.1.dev1.dist-info/LICENSE
deephaven_plugin_voice_table-0.0.1.dev1.dist-info/METADATA
deephaven_plugin_voice_table-0.0.1.dev1.dist-info/WHEEL
deephaven_plugin_voice_table-0.0.1.dev1.dist-info/top_level.txt
deephaven_plugin_voice_table-0.0.1.dev1.dist-info/RECORD
