Metadata-Version: 2.1
Name: deephaven-plugin-voice-table
Version: 0.0.1.dev1
Summary: deephaven.ui plugin to use voice to control a table
Author: Mike Bender
Author-email: mikebender@deephaven.io
Keywords: deephaven,plugin,microphone,voice,table,deephaven.ui
Platform: any
License-File: LICENSE
Requires-Dist: deephaven-plugin-ui
Requires-Dist: deephaven-plugin-microphone
Requires-Dist: openai-whisper==20231117
Requires-Dist: rapidfuzz
